dxspaces/__init__.py
dxspaces/dx_data.py
DXSpaces-0.0.8.dist-info/LICENSE
DXSpaces-0.0.8.dist-info/METADATA
DXSpaces-0.0.8.dist-info/WHEEL
DXSpaces-0.0.8.dist-info/top_level.txt
DXSpaces-0.0.8.dist-info/RECORD
