Metadata-Version: 2.1
Name: DXSpaces
Version: 0.0.8
Summary: Client library for RESTful DataSpaces
Home-page: https://github.com/sci-ndp/dxspaces
Author: Philip Davis
Author-email: philip.davis@sci.utah.edu
License-File: LICENSE
Requires-Dist: dill
Requires-Dist: numpy<2
Requires-Dist: pydantic
Requires-Dist: requests
